OwlSense/__init__.py
OwlSense/main.py
OwlSense-0.7.dist-info/METADATA
OwlSense-0.7.dist-info/WHEEL
OwlSense-0.7.dist-info/entry_points.txt
OwlSense-0.7.dist-info/top_level.txt
OwlSense-0.7.dist-info/RECORD
