Metadata-Version: 2.2
Name: OwlSense
Version: 0.7
Summary: Python lib for basic&advance AI,ML
Author: sebinmon.vr
Author-email: nthn8777@gmail.com
License: MIT
Requires-Dist: openai==0.28
Dynamic: author
Dynamic: author-email
Dynamic: license
Dynamic: requires-dist
Dynamic: summary
